client/__init__.py
client/msgr_client.py
client/client/__init__.py
client/client/add_contact.py
client/client/client_database.py
client/client/del_contact.py
client/client/main_window.py
client/client/main_window_conv.py
client/client/start_dialog.py
client/client/transport.py
client/common/__init__.py
client/common/utils.py
client/common/variables.py
client/log/__init__.py
client/log/client_log_config.py
client/log/server_log_config.py
client/tests/__init__.py
client/tests/test_client.py
client/tests/test_server.py
client/tests/test_utils.py
py_mess_gb_04_22_client-0.3.1.dist-info/METADATA
py_mess_gb_04_22_client-0.3.1.dist-info/WHEEL
py_mess_gb_04_22_client-0.3.1.dist-info/top_level.txt
py_mess_gb_04_22_client-0.3.1.dist-info/RECORD
